apiMoneyFusion/PaymentClient.py
apiMoneyFusion/__init__.py
apiMoneyFusion-0.1.3.dist-info/METADATA
apiMoneyFusion-0.1.3.dist-info/WHEEL
apiMoneyFusion-0.1.3.dist-info/top_level.txt
apiMoneyFusion-0.1.3.dist-info/RECORD
