Metadata-Version: 2.2
Name: apiMoneyFusion
Version: 0.1.3
Summary: API pour gérer la transactions dans fusion Money pour python
Home-page: https://github.com/AssemienDev/docs.moneyfusion.net.git
Author: Assemien Dev
Author-email: sidjaneassemien1@gmail.com
Classifier: Programming Language :: Python :: 3
Classifier: License :: OSI Approved :: MIT License
Classifier: Operating System :: OS Independent
Requires-Python: >=3.6
Dynamic: author
Dynamic: author-email
Dynamic: classifier
Dynamic: description
Dynamic: description-content-type
Dynamic: home-page
Dynamic: requires-python
Dynamic: summary
